Workbook
Name aporte: APP!$D$17
Name patrimonio: APP!$D$20
Name qtde_anos: APP!$D$18
Name rendimento_carteira: APP!$D$13
Name salario: APP!$D$12
Name sugestao_investimo: APP!$D$14
Name taxa_mensal: APP!$D$19

Sheet APP
B11: CONFIGURAÇÕES
B12: Salário | D12: 5000
B13: Rendimento Carteira | D13: 0.006
B14: Sugestão de investimento | D14: =salario*30% -> 1500
B16: INVESTIMENTO MENSAL
B17: Quanto investir por mês? | D17: 500
B18: Por quantos anos? | D18: 3
B19: Taxa de rendimentos mensal? | D19: 0.01079
B20: Patrimônio acumulado? | D20: =FV(taxa_mensal,qtde_anos*12,aporte*-1) -> 21854.187
B21: Dividendos mensais? | D21: =patrimonio*rendimento_carteira -> 131.12512
B23: Cenários | D23: dividendo
A24: 2 | B24: Quanto em 2 anos? | C24: =FV($D$19,$A24*12,$D$17*(-1)) -> 13613.814 | D24: =C24*rendimento_carteira -> 81.682882
A25: 5 | B25: Quanto em 5 anos? | C25: =FV($D$19,$A25*12,$D$17*(-1)) -> 41888.457 | D25: =C25*rendimento_carteira -> 251.33074
A26: 10 | B26: Quanto em 10 anos? | C26: =FV($D$19,$A26*12,$D$17*(-1)) -> 121642.11 | D26: =C26*rendimento_carteira -> 729.85264
A27: 20 | B27: Quanto em 20 anos? | C27: =FV($D$19,$A27*12,$D$17*(-1)) -> 562599.2 | D27: =C27*rendimento_carteira -> 3375.5952
A28: 30 | B28: Quanto em 30 anos? | C28: =FV($D$19,$A28*12,$D$17*(-1)) -> 2161084.8 | D28: =C28*rendimento_carteira -> 12966.509
B31: Perfil | C31: Conservador
B32: VALOR A SER INVESTIDO POR MÊS | C32: =aporte -> 500
B34: TIPO DE FII | C34: Percentual Sugerido | D34: Valores
B35: PAPEL | C35: =VLOOKUP($C$31&"-"&B35,Planilha2!$A$1:$D$18,4,0) -> 0.3 | D35: =$C$32*C35 -> 150
B36: TIJOLO | C36: =VLOOKUP($C$31&"-"&B36,Planilha2!$A$1:$D$18,4,0) -> 0.5 | D36: =$C$32*C36 -> 250
B37: HÍBRIDO | C37: =VLOOKUP($C$31&"-"&B37,Planilha2!$A$1:$D$18,4,0) -> 0.1 | D37: =$C$32*C37 -> 50
B38: FOFs | C38: =VLOOKUP($C$31&"-"&B38,Planilha2!$A$1:$D$18,4,0) -> 0.1 | D38: =$C$32*C38 -> 50
B39: DESENVOLVIMENTO | C39: =VLOOKUP($C$31&"-"&B39,Planilha2!$A$1:$D$18,4,0) -> 0 | D39: =$C$32*C39 -> 0
B40: HOTELARIAS | C40: =VLOOKUP($C$31&"-"&B40,Planilha2!$A$1:$D$18,4,0) -> 0 | D40: =$C$32*C40 -> 0
D41: =SUM(D35:D40) -> 500

Sheet Planilha2
A1: =B1&"-"&C1 -> Conservador-PAPEL | B1: Conservador | C1: PAPEL | D1: 0.3
A2: =B2&"-"&C2 -> Conservador-TIJOLO | B2: Conservador | C2: TIJOLO | D2: 0.5
A3: =B3&"-"&C3 -> Conservador-HÍBRIDO | B3: Conservador | C3: HÍBRIDO | D3: 0.1
A4: =B4&"-"&C4 -> Conservador-FOFs | B4: Conservador | C4: FOFs | D4: 0.1
A5: =B5&"-"&C5 -> Conservador-DESENVOLVIMENTO | B5: Conservador | C5: DESENVOLVIMENTO | D5: 0
A6: =B6&"-"&C6 -> Conservador-HOTELARIAS | B6: Conservador | C6: HOTELARIAS | D6: 0
A7: =B7&"-"&C7 -> Moderado-PAPEL | B7: Moderado | C7: PAPEL | D7: 0.32
A8: =B8&"-"&C8 -> Moderado-TIJOLO | B8: Moderado | C8: TIJOLO | D8: 0.4
A9: =B9&"-"&C9 -> Moderado-HÍBRIDO | B9: Moderado | C9: HÍBRIDO | D9: 0.08
A10: =B10&"-"&C10 -> Moderado-FOFs | B10: Moderado | C10: FOFs | D10: 0.1
A11: =B11&"-"&C11 -> Moderado-DESENVOLVIMENTO | B11: Moderado | C11: DESENVOLVIMENTO | D11: 0.1
A12: =B12&"-"&C12 -> Moderado-HOTELARIAS | B12: Moderado | C12: HOTELARIAS | D12: 0.1
... A18: =B18&"-"&C18 -> Agressivo-HOTELARIAS | B18: Agressivo | C18: HOTELARIAS | D18: 0.1
